MANIFEST.in
README.md
setup.py
dns_shark/__init__.py
dns_shark/__main__.py
dns_shark/command_line_parsing.py
dns_shark/dns_message.py
dns_shark/dns_message_utilities.py
dns_shark/dns_question.py
dns_shark/dns_resolver.py
dns_shark/domain_name_handling.py
dns_shark/resolver_core.py
dns_shark/resource_record.py
dns_shark.egg-info/PKG-INFO
dns_shark.egg-info/SOURCES.txt
dns_shark.egg-info/dependency_links.txt
dns_shark.egg-info/entry_points.txt
dns_shark.egg-info/top_level.txt
dns_shark/errors/__init__.py
dns_shark/errors/dns_format_error.py
dns_shark/errors/dns_name_error.py
dns_shark/errors/dns_no_matching_resource_record_error.py
dns_shark/errors/dns_not_implemented_error.py
dns_shark/errors/dns_refused_error.py
dns_shark/errors/dns_server_failure_error.py
dns_shark/errors/dns_shark_error.py
dns_shark/errors/dns_zero_counter_error.py
test/test_command_line_parsing.py
test/test_dns_message.py
test/test_dns_message_utilities.py
test/test_dns_question.py
test/test_domain_name_handling.py
test/test_main.py
test/test_resource_record.py