Metadata-Version: 2.1
Name: dns-shark
Version: 1.0.0
Summary: A simple DNS resolver that can resolve a domain name to either an IPv4 or IPv6 address.
Home-page: https://github.com/jmiiller/dns_shark
Author: Jeffrey Miiller
Author-email: jeffrey.miiller@gmail.com
License: MIT
Platform: UNKNOWN
Classifier: License :: OSI Approved :: MIT License
Classifier: Development Status :: 4 - Beta
Classifier: Environment :: Console
Classifier: Topic :: Internet :: Name Service (DNS)
Classifier: Topic :: Software Development :: Version Control :: Git
Classifier: Programming Language :: Python :: 3.6
Classifier: Programming Language :: Python :: 3.7
Classifier: Programming Language :: Python :: 3.8
